setup.py
django_kvmodel.egg-info/PKG-INFO
django_kvmodel.egg-info/SOURCES.txt
django_kvmodel.egg-info/dependency_links.txt
django_kvmodel.egg-info/requires.txt
django_kvmodel.egg-info/top_level.txt
kvmodel/__init__.py
kvmodel/fields.py
kvmodel/models.py
kvmodel/serializers.py
kvmodel/settings.py
kvmodel/subclassing.py
kvmodel/tests.py