Metadata-Version: 1.0
Name: django-kvmodel
Version: 0.1.1
Summary: A package that helps creating django key-value models easily.
Home-page: https://github.com/amdorra/django-kvmodel
Author: Abdallah Dorra
Author-email: amdorra@gmail.com
License: The MIT License (MIT)
